bubot/devices/ThermostatSML1000/ThermostatSML1000.json
bubot/devices/ThermostatSML1000/ThermostatSML1000.py
bubot/devices/ThermostatSML1000/__init__.py
bubot/devices/ThermostatSML1000/lib/TestThermostatSML1000.py
bubot/devices/ThermostatSML1000/lib/ThermostatSML1000.json
bubot/devices/ThermostatSML1000/lib/ThermostatSML1000.py
bubot_ThermostatSML1000-0.0.1.dist-info/LICENSE
bubot_ThermostatSML1000-0.0.1.dist-info/METADATA
bubot_ThermostatSML1000-0.0.1.dist-info/WHEEL
bubot_ThermostatSML1000-0.0.1.dist-info/top_level.txt
bubot_ThermostatSML1000-0.0.1.dist-info/RECORD
