Metadata-Version: 2.1
Name: bubot-ThermostatSML1000
Version: 0.0.1
Summary: Modbus bridge for Bubot
Home-page: https://github.com/businka/bubot_ThermostatSML1000
Author: Razgovorov Mikhail
Author-email: 1338833@gmail.com
License: UNKNOWN
Platform: UNKNOWN
Classifier: Programming Language :: Python :: 3
Classifier: License :: OSI Approved :: Apache Software License
Classifier: Operating System :: OS Independent
Classifier: Framework :: AsyncIO
Requires-Python: >=3.5.3
Requires-Dist: bubot-Core
Requires-Dist: aio-modbus-client
